{
    "tiles" : [[0, 0, 0, 0, 0, 0],
               [0, 0, 0, 0, 0, 0],
               [0, 0, 0, 0, 0, 0],
               [0, 0, 0, 0, 0, 0],
               [0, 0, 1, 1, 0, 0],
               [0, 0, 0, 0, 0, 0],
               [0, 0, 0, 0, 0, 0],
               [0, 0, 0, 0, 0, 0]],
    
    "values" : [[0, 0, 0, 0, 0, 0],
                [0, 0, 0, 0, 0, 0],
                [0, 0, 0, 0, 0, 0],
                [0, 0, 0, 0, 0, 0],
                [0, 0, 3, 1, 0, 0],
                [0, 0, 0, 0, 0, 0],
                [0, 0, 0, 0, 0, 0],
                [0, 0, 0, 0, 0, 0]],
    
    "types" : [[0, 0, 0, 0, 0, 0],
               [0, 0, 0, 0, 0, 0],
               [0, 0, 0, 0, 0, 0],
               [0, 0, 0, 0, 0, 0],
               [0, 0, 1, 2, 0, 0],
               [0, 0, 0, 0, 0, 0],
               [0, 0, 0, 0, 0, 0],
               [0, 0, 0, 0, 0, 0]],
    
    "target" : 4,
    "moves" : 1,
    "gameMode" : 0,
    "idealScore" : 70,
}
